pickle_openai/VERSION
pickle_openai/__init__.py
pickle_openai-0.1.0.dist-info/LICENSE
pickle_openai-0.1.0.dist-info/METADATA
pickle_openai-0.1.0.dist-info/WHEEL
pickle_openai-0.1.0.dist-info/RECORD
