Metadata-Version: 2.3
Name: pickle-openai
Version: 0.1.0
Summary: Securely Dumping and Loading an OpenAI Client with Pickle
License: MIT
Author: Allen Chou
Author-email: f1470891079@gmail.com
Requires-Python: >=3.11,<4
Classifier: License :: OSI Approved :: MIT License
Classifier: Programming Language :: Python :: 3
Classifier: Programming Language :: Python :: 3.11
Classifier: Programming Language :: Python :: 3.12
Classifier: Programming Language :: Python :: 3.13
Requires-Dist: cryptography
Requires-Dist: dictpress (>=0.3.0)
Requires-Dist: openai (>=1,<2)
Requires-Dist: openai-agents (>=0.1.0,<1.0.0)
Requires-Dist: pydantic (>=2)
Requires-Dist: str-or-none
Project-URL: Homepage, https://github.com/allen2c/pickle-openai
Project-URL: PyPI, https://pypi.org/project/pickle-openai/
Project-URL: Repository, https://github.com/allen2c/pickle-openai
